moodools/__init__.py
moodools/deps.py
moodools-0.2.3.dist-info/LICENSE
moodools-0.2.3.dist-info/WHEEL
moodools-0.2.3.dist-info/METADATA
moodools-0.2.3.dist-info/RECORD
