Metadata-Version: 2.1
Name: moodools
Version: 0.2.3
Summary: Moodools: tools for Odoo modules development
Home-page: https://github.com/LibrERP/Pylibs/
License: UNKNOWN
Author: Marco Tosato
Author-email: marco.tosato@didotech.com
Requires-Python: >= 3.6
Classifier: Programming Language :: Python :: 3
Classifier: Operating System :: OS Independent
Classifier: Development Status :: 5 - Production/Stable
Classifier: License :: OSI Approved :: GNU Lesser General Public License v3 (LGPLv3)
Classifier: Framework :: Odoo
Requires-Dist: graphviz >=0.13
Requires-Dist: pytest >=2.7.3 ; extra == "test"
Requires-Dist: pytest-cov ; extra == "test"
Requires-Dist: python-dateutil ; extra == "test"
Provides-Extra: dev
Provides-Extra: doc
Provides-Extra: test
